MANIFEST.in
README.md
setup.py
pixie_python.egg-info/PKG-INFO
pixie_python.egg-info/SOURCES.txt
pixie_python.egg-info/dependency_links.txt
pixie_python.egg-info/top_level.txt
src/pixie/__init__.py
src/pixie/libpixie.dylib
src/pixie/libpixie.so
src/pixie/pixie.dll
src/pixie/pixie.py